viff.py
viffIO-0.0.1.dist-info/LICENSE
viffIO-0.0.1.dist-info/METADATA
viffIO-0.0.1.dist-info/WHEEL
viffIO-0.0.1.dist-info/top_level.txt
viffIO-0.0.1.dist-info/RECORD
