Metadata-Version: 2.1
Name: viffIO
Version: 0.0.1
Summary: Read and write old Khoros/VisiQuest viff and xv formats
Home-page: https://github.com/patrick-c-odriscoll/viff-xv
Author: Patrick C O'Driscoll
Author-email: patrick.c.odriscoll@gmail.com
License: MIT
Keywords: viff xv khoros visiquest
Platform: UNKNOWN
Classifier: Development Status :: 4 - Beta
Classifier: Intended Audience :: Developers
Classifier: License :: OSI Approved :: MIT License
Classifier: Programming Language :: Python :: 3 :: Only
Requires-Dist: numpy
